krakenit/__init__.py
krakenit/definitions.py
krakenit/krakenit.py
krakenit/cli/__init__.py
krakenit/cli/config.py
krakenit/cli/inventory.py
krakenit/cli/main.py
krakenit/cli/publish.py
krakenit/cli/script.py
krakenit/cli/setup.py
krakenit/cli/surreal.py
krakenit/cli/sync.py
krakenit/cli/task.py
krakenit/cli/wingdbstub.py
krakenit/cli/workspace.py
krakenit/helpers/__init__.py
krakenit/helpers/faker.py
krakenit/helpers/general.py
krakenit/helpers/loaders.py
krakenit/helpers/models.py
krakenit/helpers/surreal.py
krakenit/logic/__init__.py
krakenit/logic/crawler.py
krakenit/logic/inventory.py
krakenit/logic/krakenit.py
krakenit/mappers/__init__.py
krakenit/mappers/inventory.py
krakenit/models/__init__.py
krakenit/models/base.py
krakenit/models/config.py
krakenit/models/enums.py
krakenit/models/inventory.py
krakenit/models/krakenit.py
krakenit/models/script.py
krakenit/models/task.py
krakenit/ports/__init__.py
krakenit/ports/preferences.py
krakenit/storage/__init__.py
krakenit/storage/surreal.py
krakenit-0.1.0.dist-info/AUTHORS.rst
krakenit-0.1.0.dist-info/LICENSE
krakenit-0.1.0.dist-info/METADATA
krakenit-0.1.0.dist-info/WHEEL
krakenit-0.1.0.dist-info/entry_points.txt
krakenit-0.1.0.dist-info/top_level.txt
krakenit-0.1.0.dist-info/RECORD
