Metadata-Version: 2.1
Name: krakenit
Version: 0.1.0
Summary: Multi Purpose Crawler
Home-page: https://github.com/asterio.gonzalez/krakenit
Author: Asterio Gonzalez
Author-email: asterio.gonzalez@gmail.com
License: MIT license
Keywords: krakenit
Classifier: Development Status :: 2 - Pre-Alpha
Classifier: Intended Audience :: Developers
Classifier: License :: OSI Approved :: MIT License
Classifier: Natural Language :: English
Classifier: Programming Language :: Python :: 3.10
Classifier: Programming Language :: Python :: 3.11
Requires-Python: >=3.10
License-File: LICENSE
License-File: AUTHORS.rst
Requires-Dist: agptools>=0.1.85
Requires-Dist: syncmodels>=0.1.85
Requires-Dist: pydantic
Requires-Dist: datamodel-code-generator
Requires-Dist: datamodel-code-generator[http]
Requires-Dist: datamodel-code-generator[graphql]
Requires-Dist: aiohttp
Requires-Dist: aiocache
Requires-Dist: Click
Requires-Dist: glom
Requires-Dist: jmespath
Requires-Dist: fastapi
Requires-Dist: geopy
Requires-Dist: requests
Requires-Dist: rich
Requires-Dist: surrealist
Requires-Dist: uvicorn
Requires-Dist: uvloop
Requires-Dist: watchfiles
Requires-Dist: websockets>=11.0
Requires-Dist: faker
